MANIFEST.in
README.rst
setup.py
pyca/__init__.py
pyca/__main__.py
pyca/agentstate.py
pyca/capture.py
pyca/config.py
pyca/db.py
pyca/ingest.py
pyca/schedule.py
pyca/utils.py
pyca.egg-info/PKG-INFO
pyca.egg-info/SOURCES.txt
pyca.egg-info/dependency_links.txt
pyca.egg-info/entry_points.txt
pyca.egg-info/requires.txt
pyca.egg-info/top_level.txt
pyca/ui/__init__.py
pyca/ui/jsonapi.py
pyca/ui/process_status_collector.py
pyca/ui/recordings_collector.py
pyca/ui/utils.py
pyca/ui/static/func.505dd7ab.css
pyca/ui/static/func.d1932981.js
pyca/ui/static/func.d1932981.js.map
pyca/ui/static/index.html
pyca/ui/static/style.7e280de9.css
pyca/ui/static/style.7e280de9.css.map
tests/__init__.py
tests/test_agentstate.py
tests/test_capture.py
tests/test_config.py
tests/test_db.py
tests/test_ingest.py
tests/test_main.py
tests/test_restapi.py
tests/test_schedule.py
tests/test_ui.py
tests/test_utils.py
tests/tools.py