Metadata-Version: 2.1
Name: pyca
Version: 4.4
Summary: Opencast Capture Agent
Home-page: https://github.com/opencast/pyCA
Author: Lars Kiesow
Author-email: lkiesow@uos.de
License: LGPLv3
Platform: UNKNOWN
